Workbook

Sheet Assumptions
A1: NEXA — Financial Model (assumptions)
A3: Starting active customers | B3: 2
A4: New customers in month 1 | B4: 3
A5: Monthly growth in new customers | B5: 0.08
A6: Monthly logo churn | B6: 0.03
A7: Blended ARPA (€/customer/month) | B7: 1200
A8: Gross margin | B8: 0.8
A9: Sales & marketing (€/mo, m1) | B9: 12000
A10: R&D (€/mo, m1) | B10: 18000
A11: G&A (€/mo, m1) | B11: 6000
A12: Monthly opex growth | B12: 0.04
A13: CAC (€/customer) | B13: 2500

Sheet Model
A1: Month | B1: New customers | C1: Churned | D1: Active customers | E1: MRR | F1: ARR | G1: COGS | H1: Gross profit | I1: S&M | J1: R&D | K1: G&A | L1: EBITDA | M1: Cumulative cash
A2: 1 | B2: =Assumptions!$B$4 | C2: 0 | D2: =Assumptions!$B$3+B2-C2 | E2: =D2*Assumptions!$B$7 | F2: =E2*12 | G2: =E2*(1-Assumptions!$B$8) | H2: =E2-G2 | I2: =Assumptions!$B$9*(1+Assumptions!$B$12)^0 | J2: =Assumptions!$B$10*(1+Assumptions!$B$12)^0 | K2: =Assumptions!$B$11*(1+Assumptions!$B$12)^0 | L2: =H2-I2-J2-K2 | M2: =L2
A3: 2 | B3: =B2*(1+Assumptions!$B$5) | C3: =D2*Assumptions!$B$6 | D3: =D2+B3-C3 | E3: =D3*Assumptions!$B$7 | F3: =E3*12 | G3: =E3*(1-Assumptions!$B$8) | H3: =E3-G3 | I3: =Assumptions!$B$9*(1+Assumptions!$B$12)^1 | J3: =Assumptions!$B$10*(1+Assumptions!$B$12)^1 | K3: =Assumptions!$B$11*(1+Assumptions!$B$12)^1 | L3: =H3-I3-J3-K3 | M3: =M2+L3
A4: 3 | B4: =B3*(1+Assumptions!$B$5) | C4: =D3*Assumptions!$B$6 | D4: =D3+B4-C4 | E4: =D4*Assumptions!$B$7 | F4: =E4*12 | G4: =E4*(1-Assumptions!$B$8) | H4: =E4-G4 | I4: =Assumptions!$B$9*(1+Assumptions!$B$12)^2 | J4: =Assumptions!$B$10*(1+Assumptions!$B$12)^2 | K4: =Assumptions!$B$11*(1+Assumptions!$B$12)^2 | L4: =H4-I4-J4-K4 | M4: =M3+L4
A5: 4 | B5: =B4*(1+Assumptions!$B$5) | C5: =D4*Assumptions!$B$6 | D5: =D4+B5-C5 | E5: =D5*Assumptions!$B$7 | F5: =E5*12 | G5: =E5*(1-Assumptions!$B$8) | H5: =E5-G5 | I5: =Assumptions!$B$9*(1+Assumptions!$B$12)^3 | J5: =Assumptions!$B$10*(1+Assumptions!$B$12)^3 | K5: =Assumptions!$B$11*(1+Assumptions!$B$12)^3 | L5: =H5-I5-J5-K5 | M5: =M4+L5
A6: 5 | B6: =B5*(1+Assumptions!$B$5) | C6: =D5*Assumptions!$B$6 | D6: =D5+B6-C6 | E6: =D6*Assumptions!$B$7 | F6: =E6*12 | G6: =E6*(1-Assumptions!$B$8) | H6: =E6-G6 | I6: =Assumptions!$B$9*(1+Assumptions!$B$12)^4 | J6: =Assumptions!$B$10*(1+Assumptions!$B$12)^4 | K6: =Assumptions!$B$11*(1+Assumptions!$B$12)^4 | L6: =H6-I6-J6-K6 | M6: =M5+L6
A7: 6 | B7: =B6*(1+Assumptions!$B$5) | C7: =D6*Assumptions!$B$6 | D7: =D6+B7-C7 | E7: =D7*Assumptions!$B$7 | F7: =E7*12 | G7: =E7*(1-Assumptions!$B$8) | H7: =E7-G7 | I7: =Assumptions!$B$9*(1+Assumptions!$B$12)^5 | J7: =Assumptions!$B$10*(1+Assumptions!$B$12)^5 | K7: =Assumptions!$B$11*(1+Assumptions!$B$12)^5 | L7: =H7-I7-J7-K7 | M7: =M6+L7
A8: 7 | B8: =B7*(1+Assumptions!$B$5) | C8: =D7*Assumptions!$B$6 | D8: =D7+B8-C8 | E8: =D8*Assumptions!$B$7 | F8: =E8*12 | G8: =E8*(1-Assumptions!$B$8) | H8: =E8-G8 | I8: =Assumptions!$B$9*(1+Assumptions!$B$12)^6 | J8: =Assumptions!$B$10*(1+Assumptions!$B$12)^6 | K8: =Assumptions!$B$11*(1+Assumptions!$B$12)^6 | L8: =H8-I8-J8-K8 | M8: =M7+L8
A9: 8 | B9: =B8*(1+Assumptions!$B$5) | C9: =D8*Assumptions!$B$6 | D9: =D8+B9-C9 | E9: =D9*Assumptions!$B$7 | F9: =E9*12 | G9: =E9*(1-Assumptions!$B$8) | H9: =E9-G9 | I9: =Assumptions!$B$9*(1+Assumptions!$B$12)^7 | J9: =Assumptions!$B$10*(1+Assumptions!$B$12)^7 | K9: =Assumptions!$B$11*(1+Assumptions!$B$12)^7 | L9: =H9-I9-J9-K9 | M9: =M8+L9
A10: 9 | B10: =B9*(1+Assumptions!$B$5) | C10: =D9*Assumptions!$B$6 | D10: =D9+B10-C10 | E10: =D10*Assumptions!$B$7 | F10: =E10*12 | G10: =E10*(1-Assumptions!$B$8) | H10: =E10-G10 | I10: =Assumptions!$B$9*(1+Assumptions!$B$12)^8 | J10: =Assumptions!$B$10*(1+Assumptions!$B$12)^8 | K10: =Assumptions!$B$11*(1+Assumptions!$B$12)^8 | L10: =H10-I10-J10-K10 | M10: =M9+L10
A11: 10 | B11: =B10*(1+Assumptions!$B$5) | C11: =D10*Assumptions!$B$6 | D11: =D10+B11-C11 | E11: =D11*Assumptions!$B$7 | F11: =E11*12 | G11: =E11*(1-Assumptions!$B$8) | H11: =E11-G11 | I11: =Assumptions!$B$9*(1+Assumptions!$B$12)^9 | J11: =Assumptions!$B$10*(1+Assumptions!$B$12)^9 | K11: =Assumptions!$B$11*(1+Assumptions!$B$12)^9 | L11: =H11-I11-J11-K11 | M11: =M10+L11
A12: 11 | B12: =B11*(1+Assumptions!$B$5) | C12: =D11*Assumptions!$B$6 | D12: =D11+B12-C12 | E12: =D12*Assumptions!$B$7 | F12: =E12*12 | G12: =E12*(1-Assumptions!$B$8) | H12: =E12-G12 | I12: =Assumptions!$B$9*(1+Assumptions!$B$12)^10 | J12: =Assumptions!$B$10*(1+Assumptions!$B$12)^10 | K12: =Assumptions!$B$11*(1+Assumptions!$B$12)^10 | L12: =H12-I12-J12-K12 | M12: =M11+L12
A13: 12 | B13: =B12*(1+Assumptions!$B$5) | C13: =D12*Assumptions!$B$6 | D13: =D12+B13-C13 | E13: =D13*Assumptions!$B$7 | F13: =E13*12 | G13: =E13*(1-Assumptions!$B$8) | H13: =E13-G13 | I13: =Assumptions!$B$9*(1+Assumptions!$B$12)^11 | J13: =Assumptions!$B$10*(1+Assumptions!$B$12)^11 | K13: =Assumptions!$B$11*(1+Assumptions!$B$12)^11 | L13: =H13-I13-J13-K13 | M13: =M12+L13
A14: 13 | B14: =B13*(1+Assumptions!$B$5) | C14: =D13*Assumptions!$B$6 | D14: =D13+B14-C14 | E14: =D14*Assumptions!$B$7 | F14: =E14*12 | G14: =E14*(1-Assumptions!$B$8) | H14: =E14-G14 | I14: =Assumptions!$B$9*(1+Assumptions!$B$12)^12 | J14: =Assumptions!$B$10*(1+Assumptions!$B$12)^12 | K14: =Assumptions!$B$11*(1+Assumptions!$B$12)^12 | L14: =H14-I14-J14-K14 | M14: =M13+L14
A15: 14 | B15: =B14*(1+Assumptions!$B$5) | C15: =D14*Assumptions!$B$6 | D15: =D14+B15-C15 | E15: =D15*Assumptions!$B$7 | F15: =E15*12 | G15: =E15*(1-Assumptions!$B$8) | H15: =E15-G15 | I15: =Assumptions!$B$9*(1+Assumptions!$B$12)^13 | J15: =Assumptions!$B$10*(1+Assumptions!$B$12)^13 | K15: =Assumptions!$B$11*(1+Assumptions!$B$12)^13 | L15: =H15-I15-J15-K15 | M15: =M14+L15
A16: 15 | B16: =B15*(1+Assumptions!$B$5) | C16: =D15*Assumptions!$B$6 | D16: =D15+B16-C16 | E16: =D16*Assumptions!$B$7 | F16: =E16*12 | G16: =E16*(1-Assumptions!$B$8) | H16: =E16-G16 | I16: =Assumptions!$B$9*(1+Assumptions!$B$12)^14 | J16: =Assumptions!$B$10*(1+Assumptions!$B$12)^14 | K16: =Assumptions!$B$11*(1+Assumptions!$B$12)^14 | L16: =H16-I16-J16-K16 | M16: =M15+L16
A17: 16 | B17: =B16*(1+Assumptions!$B$5) | C17: =D16*Assumptions!$B$6 | D17: =D16+B17-C17 | E17: =D17*Assumptions!$B$7 | F17: =E17*12 | G17: =E17*(1-Assumptions!$B$8) | H17: =E17-G17 | I17: =Assumptions!$B$9*(1+Assumptions!$B$12)^15 | J17: =Assumptions!$B$10*(1+Assumptions!$B$12)^15 | K17: =Assumptions!$B$11*(1+Assumptions!$B$12)^15 | L17: =H17-I17-J17-K17 | M17: =M16+L17
A18: 17 | B18: =B17*(1+Assumptions!$B$5) | C18: =D17*Assumptions!$B$6 | D18: =D17+B18-C18 | E18: =D18*Assumptions!$B$7 | F18: =E18*12 | G18: =E18*(1-Assumptions!$B$8) | H18: =E18-G18 | I18: =Assumptions!$B$9*(1+Assumptions!$B$12)^16 | J18: =Assumptions!$B$10*(1+Assumptions!$B$12)^16 | K18: =Assumptions!$B$11*(1+Assumptions!$B$12)^16 | L18: =H18-I18-J18-K18 | M18: =M17+L18
A19: 18 | B19: =B18*(1+Assumptions!$B$5) | C19: =D18*Assumptions!$B$6 | D19: =D18+B19-C19 | E19: =D19*Assumptions!$B$7 | F19: =E19*12 | G19: =E19*(1-Assumptions!$B$8) | H19: =E19-G19 | I19: =Assumptions!$B$9*(1+Assumptions!$B$12)^17 | J19: =Assumptions!$B$10*(1+Assumptions!$B$12)^17 | K19: =Assumptions!$B$11*(1+Assumptions!$B$12)^17 | L19: =H19-I19-J19-K19 | M19: =M18+L19
A20: 19 | B20: =B19*(1+Assumptions!$B$5) | C20: =D19*Assumptions!$B$6 | D20: =D19+B20-C20 | E20: =D20*Assumptions!$B$7 | F20: =E20*12 | G20: =E20*(1-Assumptions!$B$8) | H20: =E20-G20 | I20: =Assumptions!$B$9*(1+Assumptions!$B$12)^18 | J20: =Assumptions!$B$10*(1+Assumptions!$B$12)^18 | K20: =Assumptions!$B$11*(1+Assumptions!$B$12)^18 | L20: =H20-I20-J20-K20 | M20: =M19+L20
A21: 20 | B21: =B20*(1+Assumptions!$B$5) | C21: =D20*Assumptions!$B$6 | D21: =D20+B21-C21 | E21: =D21*Assumptions!$B$7 | F21: =E21*12 | G21: =E21*(1-Assumptions!$B$8) | H21: =E21-G21 | I21: =Assumptions!$B$9*(1+Assumptions!$B$12)^19 | J21: =Assumptions!$B$10*(1+Assumptions!$B$12)^19 | K21: =Assumptions!$B$11*(1+Assumptions!$B$12)^19 | L21: =H21-I21-J21-K21 | M21: =M20+L21
A22: 21 | B22: =B21*(1+Assumptions!$B$5) | C22: =D21*Assumptions!$B$6 | D22: =D21+B22-C22 | E22: =D22*Assumptions!$B$7 | F22: =E22*12 | G22: =E22*(1-Assumptions!$B$8) | H22: =E22-G22 | I22: =Assumptions!$B$9*(1+Assumptions!$B$12)^20 | J22: =Assumptions!$B$10*(1+Assumptions!$B$12)^20 | K22: =Assumptions!$B$11*(1+Assumptions!$B$12)^20 | L22: =H22-I22-J22-K22 | M22: =M21+L22
A23: 22 | B23: =B22*(1+Assumptions!$B$5) | C23: =D22*Assumptions!$B$6 | D23: =D22+B23-C23 | E23: =D23*Assumptions!$B$7 | F23: =E23*12 | G23: =E23*(1-Assumptions!$B$8) | H23: =E23-G23 | I23: =Assumptions!$B$9*(1+Assumptions!$B$12)^21 | J23: =Assumptions!$B$10*(1+Assumptions!$B$12)^21 | K23: =Assumptions!$B$11*(1+Assumptions!$B$12)^21 | L23: =H23-I23-J23-K23 | M23: =M22+L23
A24: 23 | B24: =B23*(1+Assumptions!$B$5) | C24: =D23*Assumptions!$B$6 | D24: =D23+B24-C24 | E24: =D24*Assumptions!$B$7 | F24: =E24*12 | G24: =E24*(1-Assumptions!$B$8) | H24: =E24-G24 | I24: =Assumptions!$B$9*(1+Assumptions!$B$12)^22 | J24: =Assumptions!$B$10*(1+Assumptions!$B$12)^22 | K24: =Assumptions!$B$11*(1+Assumptions!$B$12)^22 | L24: =H24-I24-J24-K24 | M24: =M23+L24
A25: 24 | B25: =B24*(1+Assumptions!$B$5) | C25: =D24*Assumptions!$B$6 | D25: =D24+B25-C25 | E25: =D25*Assumptions!$B$7 | F25: =E25*12 | G25: =E25*(1-Assumptions!$B$8) | H25: =E25-G25 | I25: =Assumptions!$B$9*(1+Assumptions!$B$12)^23 | J25: =Assumptions!$B$10*(1+Assumptions!$B$12)^23 | K25: =Assumptions!$B$11*(1+Assumptions!$B$12)^23 | L25: =H25-I25-J25-K25 | M25: =M24+L25
A26: 25 | B26: =B25*(1+Assumptions!$B$5) | C26: =D25*Assumptions!$B$6 | D26: =D25+B26-C26 | E26: =D26*Assumptions!$B$7 | F26: =E26*12 | G26: =E26*(1-Assumptions!$B$8) | H26: =E26-G26 | I26: =Assumptions!$B$9*(1+Assumptions!$B$12)^24 | J26: =Assumptions!$B$10*(1+Assumptions!$B$12)^24 | K26: =Assumptions!$B$11*(1+Assumptions!$B$12)^24 | L26: =H26-I26-J26-K26 | M26: =M25+L26
A27: 26 | B27: =B26*(1+Assumptions!$B$5) | C27: =D26*Assumptions!$B$6 | D27: =D26+B27-C27 | E27: =D27*Assumptions!$B$7 | F27: =E27*12 | G27: =E27*(1-Assumptions!$B$8) | H27: =E27-G27 | I27: =Assumptions!$B$9*(1+Assumptions!$B$12)^25 | J27: =Assumptions!$B$10*(1+Assumptions!$B$12)^25 | K27: =Assumptions!$B$11*(1+Assumptions!$B$12)^25 | L27: =H27-I27-J27-K27 | M27: =M26+L27
A28: 27 | B28: =B27*(1+Assumptions!$B$5) | C28: =D27*Assumptions!$B$6 | D28: =D27+B28-C28 | E28: =D28*Assumptions!$B$7 | F28: =E28*12 | G28: =E28*(1-Assumptions!$B$8) | H28: =E28-G28 | I28: =Assumptions!$B$9*(1+Assumptions!$B$12)^26 | J28: =Assumptions!$B$10*(1+Assumptions!$B$12)^26 | K28: =Assumptions!$B$11*(1+Assumptions!$B$12)^26 | L28: =H28-I28-J28-K28 | M28: =M27+L28
A29: 28 | B29: =B28*(1+Assumptions!$B$5) | C29: =D28*Assumptions!$B$6 | D29: =D28+B29-C29 | E29: =D29*Assumptions!$B$7 | F29: =E29*12 | G29: =E29*(1-Assumptions!$B$8) | H29: =E29-G29 | I29: =Assumptions!$B$9*(1+Assumptions!$B$12)^27 | J29: =Assumptions!$B$10*(1+Assumptions!$B$12)^27 | K29: =Assumptions!$B$11*(1+Assumptions!$B$12)^27 | L29: =H29-I29-J29-K29 | M29: =M28+L29
A30: 29 | B30: =B29*(1+Assumptions!$B$5) | C30: =D29*Assumptions!$B$6 | D30: =D29+B30-C30 | E30: =D30*Assumptions!$B$7 | F30: =E30*12 | G30: =E30*(1-Assumptions!$B$8) | H30: =E30-G30 | I30: =Assumptions!$B$9*(1+Assumptions!$B$12)^28 | J30: =Assumptions!$B$10*(1+Assumptions!$B$12)^28 | K30: =Assumptions!$B$11*(1+Assumptions!$B$12)^28 | L30: =H30-I30-J30-K30 | M30: =M29+L30
A31: 30 | B31: =B30*(1+Assumptions!$B$5) | C31: =D30*Assumptions!$B$6 | D31: =D30+B31-C31 | E31: =D31*Assumptions!$B$7 | F31: =E31*12 | G31: =E31*(1-Assumptions!$B$8) | H31: =E31-G31 | I31: =Assumptions!$B$9*(1+Assumptions!$B$12)^29 | J31: =Assumptions!$B$10*(1+Assumptions!$B$12)^29 | K31: =Assumptions!$B$11*(1+Assumptions!$B$12)^29 | L31: =H31-I31-J31-K31 | M31: =M30+L31
A32: 31 | B32: =B31*(1+Assumptions!$B$5) | C32: =D31*Assumptions!$B$6 | D32: =D31+B32-C32 | E32: =D32*Assumptions!$B$7 | F32: =E32*12 | G32: =E32*(1-Assumptions!$B$8) | H32: =E32-G32 | I32: =Assumptions!$B$9*(1+Assumptions!$B$12)^30 | J32: =Assumptions!$B$10*(1+Assumptions!$B$12)^30 | K32: =Assumptions!$B$11*(1+Assumptions!$B$12)^30 | L32: =H32-I32-J32-K32 | M32: =M31+L32
A33: 32 | B33: =B32*(1+Assumptions!$B$5) | C33: =D32*Assumptions!$B$6 | D33: =D32+B33-C33 | E33: =D33*Assumptions!$B$7 | F33: =E33*12 | G33: =E33*(1-Assumptions!$B$8) | H33: =E33-G33 | I33: =Assumptions!$B$9*(1+Assumptions!$B$12)^31 | J33: =Assumptions!$B$10*(1+Assumptions!$B$12)^31 | K33: =Assumptions!$B$11*(1+Assumptions!$B$12)^31 | L33: =H33-I33-J33-K33 | M33: =M32+L33
A34: 33 | B34: =B33*(1+Assumptions!$B$5) | C34: =D33*Assumptions!$B$6 | D34: =D33+B34-C34 | E34: =D34*Assumptions!$B$7 | F34: =E34*12 | G34: =E34*(1-Assumptions!$B$8) | H34: =E34-G34 | I34: =Assumptions!$B$9*(1+Assumptions!$B$12)^32 | J34: =Assumptions!$B$10*(1+Assumptions!$B$12)^32 | K34: =Assumptions!$B$11*(1+Assumptions!$B$12)^32 | L34: =H34-I34-J34-K34 | M34: =M33+L34
A35: 34 | B35: =B34*(1+Assumptions!$B$5) | C35: =D34*Assumptions!$B$6 | D35: =D34+B35-C35 | E35: =D35*Assumptions!$B$7 | F35: =E35*12 | G35: =E35*(1-Assumptions!$B$8) | H35: =E35-G35 | I35: =Assumptions!$B$9*(1+Assumptions!$B$12)^33 | J35: =Assumptions!$B$10*(1+Assumptions!$B$12)^33 | K35: =Assumptions!$B$11*(1+Assumptions!$B$12)^33 | L35: =H35-I35-J35-K35 | M35: =M34+L35
A36: 35 | B36: =B35*(1+Assumptions!$B$5) | C36: =D35*Assumptions!$B$6 | D36: =D35+B36-C36 | E36: =D36*Assumptions!$B$7 | F36: =E36*12 | G36: =E36*(1-Assumptions!$B$8) | H36: =E36-G36 | I36: =Assumptions!$B$9*(1+Assumptions!$B$12)^34 | J36: =Assumptions!$B$10*(1+Assumptions!$B$12)^34 | K36: =Assumptions!$B$11*(1+Assumptions!$B$12)^34 | L36: =H36-I36-J36-K36 | M36: =M35+L36
A37: 36 | B37: =B36*(1+Assumptions!$B$5) | C37: =D36*Assumptions!$B$6 | D37: =D36+B37-C37 | E37: =D37*Assumptions!$B$7 | F37: =E37*12 | G37: =E37*(1-Assumptions!$B$8) | H37: =E37-G37 | I37: =Assumptions!$B$9*(1+Assumptions!$B$12)^35 | J37: =Assumptions!$B$10*(1+Assumptions!$B$12)^35 | K37: =Assumptions!$B$11*(1+Assumptions!$B$12)^35 | L37: =H37-I37-J37-K37 | M37: =M36+L37

Sheet Summary
A1: NEXA — Summary
A3: Metric | B3: End of Year 1 | C3: End of Year 2 | D3: End of Year 3
A4: Active customers | B4: =Model!D14 | C4: =Model!D26 | D4: =Model!D37
A5: MRR | B5: =Model!E14 | C5: =Model!E26 | D5: =Model!E37
A6: ARR | B6: =Model!F14 | C6: =Model!F26 | D6: =Model!F37
A7: EBITDA (month) | B7: =Model!L14 | C7: =Model!L26 | D7: =Model!L37
A8: Cumulative cash | B8: =Model!M14 | C8: =Model!M26 | D8: =Model!M37
A11: Indicative valuation (ARR × multiple)
A12: Conservative (5× ARR Y3) | B12: =D6*5
A13: Base (8× ARR Y3) | B13: =D6*8
A14: Optimistic (12× ARR Y3, AI premium) | B14: =D6*12
A16: Note: illustrative model. Multiples are general SaaS rules of thumb, not a valuation or financial advice.
